webprobe/__init__.py
webprobe/_webprobe.py
webprobe/db/400_blacklist.txt
webprobe/db/403_blacklist.txt
webprobe/db/500_blacklist.txt
webprobe/db/dicc.txt
webprobe/db/user-agents.txt
webprobe/lib/__init__.py
webprobe/lib/connection/__init__.py
webprobe/lib/connection/request_exception.py
webprobe/lib/connection/requester.py
webprobe/lib/connection/response.py
webprobe/lib/controller/__init__.py
webprobe/lib/controller/controller.py
webprobe/lib/core/__init__.py
webprobe/lib/core/argument_parser.py
webprobe/lib/core/dictionary.py
webprobe/lib/core/fuzzer.py
webprobe/lib/core/path.py
webprobe/lib/core/raw.py
webprobe/lib/core/report_manager.py
webprobe/lib/core/scanner.py
webprobe/lib/core/config/default.conf
webprobe/lib/output/__init__.py
webprobe/lib/output/colors.py
webprobe/lib/output/silent_output.py
webprobe/lib/output/verbose_output.py
webprobe/lib/parse/__init__.py
webprobe/lib/parse/configparser.py
webprobe/lib/parse/headers.py
webprobe/lib/parse/similarity.py
webprobe/lib/reports/__init__.py
webprobe/lib/reports/base.py
webprobe/lib/reports/csv_report.py
webprobe/lib/reports/html_report.py
webprobe/lib/reports/json_report.py
webprobe/lib/reports/markdown_report.py
webprobe/lib/reports/plain_text_report.py
webprobe/lib/reports/simple_report.py
webprobe/lib/reports/xml_report.py
webprobe/lib/utils/__init__.py
webprobe/lib/utils/file.py
webprobe/lib/utils/fmt.py
webprobe/lib/utils/ip.py
webprobe/lib/utils/random.py
webprobe/lib/utils/range.py
webprobe/lib/utils/size.py
webprobe/lib/utils/timer.py
webprobe/thirdparty/__init__.py
webprobe/thirdparty/socks.py
webprobe/thirdparty/sockshandler.py
webprobe/thirdparty/sqlmap/DynamicContentParser.py
webprobe/thirdparty/sqlmap/__init__.py
webprobe-2022.3.dist-info/LICENSE
webprobe-2022.3.dist-info/METADATA
webprobe-2022.3.dist-info/WHEEL
webprobe-2022.3.dist-info/entry_points.txt
webprobe-2022.3.dist-info/top_level.txt
webprobe-2022.3.dist-info/RECORD
