Metadata-Version: 2.1
Name: webprobe
Version: 2022.3
Summary: Nifty and sophisticated web scanner
Home-page: https://github.com/scalabli
Author: Gerrishon Sirere
Author-email: scalabli@proton.me
Maintainer: Scalabli.
Maintainer-email: scalabli@proton.me
License: MIT
Project-URL: Donate, https://ko-fi.com/scalabli
Project-URL: Documentation, https://github.com/scalabli/webprobe
Project-URL: Changes, https://github.com/scalabli/webprobe
Project-URL: Source Code, https://github.com/scalabli/webprobe
Project-URL: Issue Tracker, https://github.com/scalabli/webprobe/issues/
Project-URL: Twitter, https://twitter.com/scalabli
Project-URL: Chat, https://gitter.im/scalabli
Keywords: infosec,bug bounty,pentesting,security
Classifier: Development Status :: 5 - Production/Stable
Classifier: Intended Audience :: Developers
Classifier: Environment :: Console
Classifier: License :: OSI Approved :: MIT License
Classifier: Operating System :: OS Independent
Classifier: Programming Language :: Python :: 3.8
Classifier: Programming Language :: Python :: 3.9
Classifier: Programming Language :: Python :: 3.10
Requires-Python: >=3.8
License-File: LICENSE
Requires-Dist: cryptography (>=2.8)
Requires-Dist: PySocks (>=1.6.8)
Requires-Dist: cffi (>=1.14.0)
Requires-Dist: quo (>=2022.8.1)
Requires-Dist: Jinja2 (>=3.0.0)
Requires-Dist: certifi (>=2017.4.17)
Requires-Dist: urllib3 (>=1.21.1)
Requires-Dist: defusedxml (>=0.7.0)
Requires-Dist: markupsafe (>=2.0.0)
Requires-Dist: pyopenssl (>=21.0.0)
Requires-Dist: idna (>=2.5)
Requires-Dist: chardet (>=3.0.2)
Requires-Dist: charset-normalizer (~=2.0.0)
Requires-Dist: requests-ntlm (>=1.1.0)
Requires-Dist: colorama (>=0.4.4)
Requires-Dist: ntlm-auth (>=1.5.0)
Requires-Dist: pyparsing (>=2.4.7)
